tyaml/__init__.py
tyaml/dumper.py
tyaml/loader.py
tyaml/types.py
pyyaml_typed-0.1.3.dist-info/LICENSE
pyyaml_typed-0.1.3.dist-info/WHEEL
pyyaml_typed-0.1.3.dist-info/METADATA
pyyaml_typed-0.1.3.dist-info/RECORD
