Metadata-Version: 2.1
Name: pyyaml-typed
Version: 0.1.3
Summary: PyYAML dumper/loader using field descriptions in class comments
Home-page: https://github.com/outcatcher/pyyaml-typed
License: MIT
Author: Anton Kachurin
Author-email: katchuring@gmail.com
Requires-Python: >=3.7,<4.0
Classifier: License :: OSI Approved :: MIT License
Classifier: Programming Language :: Python :: 3
Classifier: Programming Language :: Python :: 3.7
Classifier: Programming Language :: Python :: 3.8
Classifier: Programming Language :: Python :: 3.9
Requires-Dist: pyyaml (>=5.3,<6.0)
Project-URL: Repository, https://github.com/outcatcher/pyyaml-typed
